irr-generator/__init__.py
irr-generator/irrgenerator.py
irrgenerator/__init__.py
irrgenerator/irrgenerator.py
irr_generator-0.0.4.dist-info/LICENSE
irr_generator-0.0.4.dist-info/METADATA
irr_generator-0.0.4.dist-info/WHEEL
irr_generator-0.0.4.dist-info/entry_points.txt
irr_generator-0.0.4.dist-info/top_level.txt
irr_generator-0.0.4.dist-info/RECORD
