Metadata-Version: 2.1
Name: irr-generator
Version: 0.0.4
Summary: Generate IRR Route Objects at scale quickly and without error
Home-page: https://github.com/jamesditrapani/irr-generator
Author: James Di Trapani
Author-email: james@ditrapani.com.au
License: UNKNOWN
Platform: UNKNOWN
Classifier: Programming Language :: Python :: 3
Classifier: Development Status :: 3 - Alpha
Classifier: Topic :: System :: Networking
Requires-Python: >=3.6
Requires-Dist: requests (>==2.25.1)
Requires-Dist: netaddr (>==0.8.0)
